visual/__init__.py
visual/interface.py
visual/lib/__init__.py
visual/lib/convenience.py
visual/lib/flags.py
visual/lib/hasher.py
visual/lib/models.py
visual/lib/storage.py
visual/lib/ui.py
pytest_visual-0.3.1.dist-info/LICENSE
pytest_visual-0.3.1.dist-info/METADATA
pytest_visual-0.3.1.dist-info/WHEEL
pytest_visual-0.3.1.dist-info/entry_points.txt
pytest_visual-0.3.1.dist-info/top_level.txt
pytest_visual-0.3.1.dist-info/RECORD
