Metadata-Version: 2.1
Name: pytest-visual
Version: 0.3.1
Home-page: https://github.com/pytest-visual/pytest-visual
Author: Kristjan Kongas
License: MIT
Classifier: Development Status :: 4 - Beta
Classifier: License :: OSI Approved :: MIT License
Classifier: Programming Language :: Python :: 3.8
Classifier: Programming Language :: Python :: 3.9
Classifier: Programming Language :: Python :: 3.10
Classifier: Programming Language :: Python :: 3.11
Classifier: Programming Language :: Python :: 3.12
Classifier: Programming Language :: Python :: 3.13
Requires-Python: >=3.8
License-File: LICENSE
Requires-Dist: pytest >=7.0.0
Requires-Dist: plotly >=5.0.0
Requires-Dist: dash >=2.0.0
Requires-Dist: dash-bootstrap-components >=1.0.0
Requires-Dist: numpy >=1.17.0
Requires-Dist: pandas >=2.0.0
Requires-Dist: graphviz >=0.17
Requires-Dist: Pillow >=8.0.0
Requires-Dist: pydantic >=2.0.0
